{
  "_fv": 28,
  "_type": "recipe",
  "definition": {
    "recipeType": "Crafting",
    "xpReward": 0.0,
    "cookingTime": 200,
    "recipeRetstackSize": 4,
    "group": "",
    "recipeShapeless": false,
    "recipeSlots": [
      {
        "value": ""
      },
      {
        "value": "Items.AMETHYST_SHARD"
      },
      {
        "value": ""
      },
      {
        "value": "CUSTOM:Pla"
      },
      {
        "value": "CUSTOM:Diode"
      },
      {
        "value": "CUSTOM:Pla"
      },
      {
        "value": ""
      },
      {
        "value": "Items.IRON_INGOT"
      },
      {
        "value": ""
      }
    ],
    "recipeReturnStack": {
      "value": "CUSTOM:LedIR"
    },
    "name": "led_ir_recipe",
    "namespace": "mod"
  }
}